universal_hex/__init__.py
universal_hex/cli.py
universal_hex/ihex.py
universal_hex/uhex.py
universal_hex/utils.py
universal_hex-0.1.0.dist-info/WHEEL
universal_hex-0.1.0.dist-info/entry_points.txt
universal_hex-0.1.0.dist-info/METADATA
universal_hex-0.1.0.dist-info/RECORD
