Metadata-Version: 2.4
Name: universal-hex
Version: 0.1.0
Summary: Create and split micro:bit Universal Hex files
Keywords: microbit,micro:bit,BBC micro:bit,hex,Intel Hex,Universal Hex
Author: Carlos Pereira Atencio
Author-email: Carlos Pereira Atencio <carlosperate@embeddedlog.com>
License-Expression: MIT
Classifier: Development Status :: 4 - Beta
Classifier: Intended Audience :: Developers
Classifier: License :: OSI Approved :: MIT License
Classifier: Programming Language :: Python :: 3
Classifier: Programming Language :: Python :: 3.9
Classifier: Programming Language :: Python :: 3.10
Classifier: Programming Language :: Python :: 3.11
Classifier: Programming Language :: Python :: 3.12
Classifier: Programming Language :: Python :: 3.13
Classifier: Programming Language :: Python :: 3.14
Classifier: Topic :: Software Development :: Embedded Systems
Requires-Dist: click>=8.1,<9
Requires-Python: >=3.9
Project-URL: Homepage, https://github.com/carlosperate/python-universal-hex
Project-URL: Repository, https://github.com/carlosperate/python-universal-hex.git
Project-URL: Issues, https://github.com/carlosperate/python-universal-hex/issues
Project-URL: Changelog, https://github.com/carlosperate/python-universal-hex/blob/main/CHANGELOG.md
